<?xml version="1.0" encoding='gb2312'?>
<hierarchy docType="SDP_MULTI-TABLE_HIERARCHY" name="bd_busitype">
	<tableName>bd_busitype</tableName>
	<pk>pk_busitype</pk>
	<sqlNo>001</sqlNo>
	<subTableGroup>
		<subTable>
			<tableName>pub_billbusiness</tableName>
			<foreignKeyColumn>pk_businesstype</foreignKeyColumn>
		    <whereCondition/>
		    <sqlNo>002</sqlNo>
			<subTableGroup>
				<subTable>
					<tableName>pub_billsource</tableName>
					<foreignKeyColumn>billbusinessid</foreignKeyColumn>
					<whereCondition/>
					<sqlNo>003</sqlNo>
					<subTableGroup/>
				</subTable>
			</subTableGroup>
		</subTable>
		<subTable>
			<tableName>pub_messagedrive</tableName>
			<foreignKeyColumn>pk_businesstype</foreignKeyColumn>
		    <whereCondition/>
		    <sqlNo>004</sqlNo>
		</subTable>
		<subTable>
			<tableName>pub_actionconstrict</tableName>
			<foreignKeyColumn>pk_businesstype</foreignKeyColumn>
		    <whereCondition/>
		    <sqlNo>005</sqlNo>
		</subTable>
		<subTable>
			<tableName>pub_billbackmsg</tableName>
			<foreignKeyColumn>pk_busitype</foreignKeyColumn>
		    <whereCondition/>
		    <sqlNo>006</sqlNo>
		</subTable>
		<subTable>
			<tableName>pub_graphbuzi</tableName>
			<foreignKeyColumn>pk_buziobject</foreignKeyColumn>
		    <whereCondition/>
		    <sqlNo>007</sqlNo>
		    <subTableGroup>
		    	<subTable>
					<tableName>pub_ufgraph</tableName>
					<foreignKeyColumn>pk_graph</foreignKeyColumn>
					<whereCondition/>
					<sqlNo>008</sqlNo>
				</subTable>
		    </subTableGroup>
		</subTable>
	</subTableGroup>
</hierarchy>